blended/__init__.py
blended/_compat.py
blended/colormap.py
blended/functions.py
blended/jinjaenv.py
blended/sets.py
blended/trimfloat.py
blended/__pycache__/__init__.cpython-311.pyc
blended/__pycache__/__init__.cpython-38.pyc
blended/__pycache__/_compat.cpython-311.pyc
blended/__pycache__/_compat.cpython-38.pyc
blended/__pycache__/colormap.cpython-311.pyc
blended/__pycache__/colormap.cpython-38.pyc
blended/__pycache__/functions.cpython-311.pyc
blended/__pycache__/functions.cpython-38.pyc
blended/__pycache__/jinjaenv.cpython-311.pyc
blended/__pycache__/jinjaenv.cpython-38.pyc
blended/__pycache__/sets.cpython-311.pyc
blended/__pycache__/sets.cpython-38.pyc
blended/__pycache__/trimfloat.cpython-311.pyc
blended/__pycache__/trimfloat.cpython-38.pyc
blended/customtags/__init__.py
blended/customtags/_compat.py
blended/customtags/_stringdefs.py
blended/customtags/arguments.py
blended/customtags/core.py
blended/customtags/decorators.py
blended/customtags/exceptions.py
blended/customtags/expr_parser.py
blended/customtags/helpers.py
blended/customtags/lexer.py
blended/customtags/middleware.py
blended/customtags/nodes.py
blended/customtags/parser.py
blended/customtags/tokens.py
blended/customtags/trimfloat.py
blended/customtags/utils.py
blended/customtags/values.py
blended/customtags/__pycache__/__init__.cpython-311.pyc
blended/customtags/__pycache__/__init__.cpython-38.pyc
blended/customtags/__pycache__/_compat.cpython-311.pyc
blended/customtags/__pycache__/_compat.cpython-38.pyc
blended/customtags/__pycache__/_stringdefs.cpython-311.pyc
blended/customtags/__pycache__/_stringdefs.cpython-38.pyc
blended/customtags/__pycache__/arguments.cpython-311.pyc
blended/customtags/__pycache__/arguments.cpython-38.pyc
blended/customtags/__pycache__/core.cpython-311.pyc
blended/customtags/__pycache__/core.cpython-38.pyc
blended/customtags/__pycache__/decorators.cpython-311.pyc
blended/customtags/__pycache__/decorators.cpython-38.pyc
blended/customtags/__pycache__/exceptions.cpython-311.pyc
graj_lang-2.0.1.dist-info/LICENSE
graj_lang-2.0.1.dist-info/METADATA
graj_lang-2.0.1.dist-info/WHEEL
graj_lang-2.0.1.dist-info/top_level.txt
graj_lang-2.0.1.dist-info/RECORD
