Metadata-Version: 2.1
Name: graj-lang
Version: 2.0.1
Summary: Blended Command Line Application
Home-page: http://blended.dbmonline.net/
Author: DBM
Author-email: pgaur@cognam.com
License: BSD
Platform: UNKNOWN
License-File: LICENSE
Requires-Dist: markupsafe (==2.1.2)
Requires-Dist: jinja2 (==3.1.2)
Requires-Dist: django (==4.1.7)
